<?xml version="1.0" encoding="UTF-8" standalone="yes"?>
<p:sldLayout xmlns:a="http://schemas.openxmlformats.org/drawingml/2006/main" xmlns:r="http://schemas.openxmlformats.org/officeDocument/2006/relationships" xmlns:p="http://schemas.openxmlformats.org/presentationml/2006/main" type="obj" preserve="1"><p:cSld name="Title and Content"><p:spTree><p:nvGrpSpPr><p:cNvPr id="1" name=""/><p:cNvGrpSpPr/><p:nvPr/></p:nvGrpSpPr><p:grpSpPr><a:xfrm><a:off x="0" y="0"/><a:ext cx="0" cy="0"/><a:chOff x="0" y="0"/><a:chExt cx="0" cy="0"/></a:xfrm></p:grpSpPr><p:sp><p:nvSpPr><p:cNvPr id="2" name="Title 1"><a:extLst><a:ext uri="{FF2B5EF4-FFF2-40B4-BE49-F238E27FC236}"><a16:creationId xmlns:a16="http://schemas.microsoft.com/office/drawing/2014/main" id="{1FC8E661-5251-8D4A-B785-44A6DB992AD8}"/></a:ext></a:extLst></p:cNvPr><p:cNvSpPr><a:spLocks noGrp="1"/></p:cNvSpPr><p:nvPr><p:ph type="title"/></p:nvPr></p:nvSpPr><p:spPr/><p:txBody><a:bodyPr/><a:lstStyle/><a:p><a:r><a:rPr lang="en-US"/><a:t>Click to edit Master title style</a:t></a:r></a:p></p:txBody></p:sp><p:sp><p:nvSpPr><p:cNvPr id="3" name="Content Placeholder 2"><a:extLst><a:ext uri="{FF2B5EF4-FFF2-40B4-BE49-F238E27FC236}"><a16:creationId xmlns:a16="http://schemas.microsoft.com/office/drawing/2014/main" id="{421805BC-2329-844A-AA01-6F2BB5F4A4AD}"/></a:ext></a:extLst></p:cNvPr><p:cNvSpPr><a:spLocks noGrp="1"/></p:cNvSpPr><p:nvPr><p:ph idx="1"/></p:nvPr></p:nvSpPr><p:spPr/><p:txBody><a:bodyPr/><a:lstStyle/><a:p><a:pPr lvl="0"/><a:r><a:rPr lang="en-US"/><a:t>Click to edit Master text styles</a:t></a:r></a:p><a:p><a:pPr lvl="1"/><a:r><a:rPr lang="en-US"/><a:t>Second level</a:t></a:r></a:p><a:p><a:pPr lvl="2"/><a:r><a:rPr lang="en-US"/><a:t>Third level</a:t></a:r></a:p><a:p><a:pPr lvl="3"/><a:r><a:rPr lang="en-US"/><a:t>Fourth level</a:t></a:r></a:p><a:p><a:pPr lvl="4"/><a:r><a:rPr lang="en-US"/><a:t>Fifth level</a:t></a:r></a:p></p:txBody></p:sp><p:sp><p:nvSpPr><p:cNvPr id="4" name="Date Placeholder 3"><a:extLst><a:ext uri="{FF2B5EF4-FFF2-40B4-BE49-F238E27FC236}"><a16:creationId xmlns:a16="http://schemas.microsoft.com/office/drawing/2014/main" id="{5D647F6D-8852-CE49-8998-68CD6DC6C6AD}"/></a:ext></a:extLst></p:cNvPr><p:cNvSpPr><a:spLocks noGrp="1"/></p:cNvSpPr><p:nvPr><p:ph type="dt" sz="half" idx="10"/></p:nvPr></p:nvSpPr><p:spPr/><p:txBody><a:bodyPr/><a:lstStyle/><a:p><a:fld id="{0F8B6A4D-56EB-1D4A-84F5-04284CCEE23F}" type="datetimeFigureOut"><a:rPr lang="en-US" smtClean="0"/><a:t>1/6/2026</a:t></a:fld><a:endParaRPr lang="en-US"/></a:p></p:txBody></p:sp><p:sp><p:nvSpPr><p:cNvPr id="5" name="Footer Placeholder 4"><a:extLst><a:ext uri="{FF2B5EF4-FFF2-40B4-BE49-F238E27FC236}"><a16:creationId xmlns:a16="http://schemas.microsoft.com/office/drawing/2014/main" id="{337B4045-E775-CD4D-8BCB-38BA6D91BAD0}"/></a:ext></a:extLst></p:cNvPr><p:cNvSpPr><a:spLocks noGrp="1"/></p:cNvSpPr><p:nvPr><p:ph type="ftr" sz="quarter" idx="11"/></p:nvPr></p:nvSpPr><p:spPr/><p:txBody><a:bodyPr/><a:lstStyle/><a:p><a:endParaRPr lang="en-US"/></a:p></p:txBody></p:sp><p:sp><p:nvSpPr><p:cNvPr id="6" name="Slide Number Placeholder 5"><a:extLst><a:ext uri="{FF2B5EF4-FFF2-40B4-BE49-F238E27FC236}"><a16:creationId xmlns:a16="http://schemas.microsoft.com/office/drawing/2014/main" id="{12D2901E-AAEB-1741-8C24-87AF4B9F1442}"/></a:ext></a:extLst></p:cNvPr><p:cNvSpPr><a:spLocks noGrp="1"/></p:cNvSpPr><p:nvPr><p:ph type="sldNum" sz="quarter" idx="12"/></p:nvPr></p:nvSpPr><p:spPr/><p:txBody><a:bodyPr/><a:lstStyle/><a:p><a:fld id="{8C6BDED9-510C-2F4F-8495-53412EF1F6DD}" type="slidenum"><a:rPr lang="en-US" smtClean="0"/><a:t>‹#›</a:t></a:fld><a:endParaRPr lang="en-US"/></a:p></p:txBody></p:sp></p:spTree><p:extLst><p:ext uri="{BB962C8B-B14F-4D97-AF65-F5344CB8AC3E}"><p14:creationId xmlns:p14="http://schemas.microsoft.com/office/powerpoint/2010/main" val="1640291137"/></p:ext></p:extLst></p:cSld><p:clrMapOvr><a:masterClrMapping/></p:clrMapOvr></p:sldLayout>